pyboke/__init__.py
pyboke/main.py
pyboke/model.py
pyboke/tmpl_render.py
pyboke/util.py
pyboke/templates/.rgignore
pyboke/templates/LICENSE.txt
pyboke/templates/article.html
pyboke/templates/article.toml
pyboke/templates/atom.xml
pyboke/templates/base.html
pyboke/templates/blog.toml
pyboke/templates/draft.md
pyboke/templates/index.html
pyboke/templates/random.html
pyboke/templates/style.css
pyboke/templates/title-index.html
pyboke/templates/years.html
pyboke/templates/themes/mvp.css
pyboke/templates/themes/new.css
pyboke/templates/themes/simple.css
pyboke/templates/themes/water.css
pyboke-0.0.5.dist-info/entry_points.txt
pyboke-0.0.5.dist-info/LICENSE
pyboke-0.0.5.dist-info/WHEEL
pyboke-0.0.5.dist-info/METADATA
pyboke-0.0.5.dist-info/RECORD
