Metadata-Version: 2.1
Name: pyboke
Version: 0.0.5
Summary: pyboke: Static Blog Generator. (尽可能简单的静态博客生成器)
Author-email: ahui <102419@gmail.com>
Requires-Python: >=3.10
Classifier: License :: OSI Approved :: MIT License
Requires-Dist: arrow
Requires-Dist: click
Requires-Dist: jinja2
Requires-Dist: tomli
Requires-Dist: mistune
Project-URL: Home, https://github.com/ahui2016/pyboke
